msrDynamics/__init__.py
msrDynamics/components.py
msrDynamics/system_objects.py
msrDynamics-0.1.0.dist-info/LICENSE
msrDynamics-0.1.0.dist-info/METADATA
msrDynamics-0.1.0.dist-info/WHEEL
msrDynamics-0.1.0.dist-info/top_level.txt
msrDynamics-0.1.0.dist-info/RECORD
