Metadata-Version: 2.1
Name: msrDynamics
Version: 0.1.0
Summary: Python API to JiTCDDE for neutronic and thermal hydraulic systems
Author: Luke Labrie-Cleary
Author-email: Luke Labrie-Cleary <lplcleary@gmail.com>
License: MIT License
Classifier: Programming Language :: Python :: 3
Classifier: License :: OSI Approved :: MIT License
Classifier: Operating System :: OS Independent
Classifier: Development Status :: 4 - Beta
Classifier: Environment :: Console
Requires-Python: >=3.6
License-File: LICENSE
Requires-Dist: jitcdde
Requires-Dist: numpy
Requires-Dist: chspy
